[
  {
    "type": "entry",
    "author": {
      "type": "card",
      "name": "Frederick Vanbrabant",
      "photo": "https://webmention.io/avatar/pbs.twimg.com/79ec01dbe39d77912093887ec2c4d304d2885330d843f45e1bbf4a69c221164a.jpg",
      "url": "https://twitter.com/maybeFrederick"
    },
    "url": "https://twitter.com/sebdedeyne/status/1181838273049743360#favorited-by-80525142",
    "published": null,
    "wm-received": "2019-10-09T08:59:58Z",
    "wm-id": 707483,
    "wm-source": "https://brid-gy.appspot.com/like/twitter/sebdedeyne/1181838273049743360/80525142",
    "wm-target": "https://sebastiandedeyne.com/migrating-my-site-to-hugo/",
    "like-of": "https://sebastiandedeyne.com/migrating-my-site-to-hugo/",
    "wm-property": "like-of",
    "wm-private": false
  },
  {
    "type": "entry",
    "author": {
      "type": "card",
      "name": "Christoph Rumpel 🤠",
      "photo": "https://webmention.io/avatar/pbs.twimg.com/6a9353f47bff347ef06aa35069a69e19064f5499e29fc411ead1250cac6b9013.jpg",
      "url": "https://twitter.com/christophrumpel"
    },
    "url": "https://twitter.com/sebdedeyne/status/1181838273049743360#favorited-by-224375889",
    "published": null,
    "wm-received": "2019-10-09T08:59:58Z",
    "wm-id": 707484,
    "wm-source": "https://brid-gy.appspot.com/like/twitter/sebdedeyne/1181838273049743360/224375889",
    "wm-target": "https://sebastiandedeyne.com/migrating-my-site-to-hugo/",
    "like-of": "https://sebastiandedeyne.com/migrating-my-site-to-hugo/",
    "wm-property": "like-of",
    "wm-private": false
  },
  {
    "type": "entry",
    "author": {
      "type": "card",
      "name": "Christoph Rumpel 🤠",
      "photo": "https://webmention.io/avatar/pbs.twimg.com/6a9353f47bff347ef06aa35069a69e19064f5499e29fc411ead1250cac6b9013.jpg",
      "url": "https://twitter.com/christophrumpel"
    },
    "url": "https://twitter.com/christophrumpel/status/1181851464886603778",
    "published": "2019-10-09T08:38:41+00:00",
    "wm-received": "2019-10-09T08:59:59Z",
    "wm-id": 707485,
    "wm-source": "https://brid-gy.appspot.com/comment/twitter/sebdedeyne/1181838273049743360/1181851464886603778",
    "wm-target": "https://sebastiandedeyne.com/migrating-my-site-to-hugo/",
    "content": {
      "html": "That's interesting. I switched some years ago from Jekyll to a Laravel app based on your Laravel app 😅 Let me know how you like Hugo!\n<a class=\"u-mention\" href=\"https://sebastiandedeyne.com/\"></a>\n<a class=\"u-mention\" href=\"https://twitter.com/GoHugoIO\"></a>\n<a class=\"u-mention\" href=\"https://twitter.com/sebdedeyne\"></a>",
      "text": "That's interesting. I switched some years ago from Jekyll to a Laravel app based on your Laravel app 😅 Let me know how you like Hugo!"
    },
    "in-reply-to": "https://sebastiandedeyne.com/migrating-my-site-to-hugo/",
    "wm-property": "in-reply-to",
    "wm-private": false
  },
  {
    "type": "entry",
    "author": {
      "type": "card",
      "name": "Frederick Vanbrabant",
      "photo": "https://webmention.io/avatar/pbs.twimg.com/79ec01dbe39d77912093887ec2c4d304d2885330d843f45e1bbf4a69c221164a.jpg",
      "url": "https://twitter.com/maybeFrederick"
    },
    "url": "https://twitter.com/maybeFrederick/status/1181856401167134720",
    "published": "2019-10-09T08:58:18+00:00",
    "wm-received": "2019-10-09T09:00:00Z",
    "wm-id": 707486,
    "wm-source": "https://brid-gy.appspot.com/comment/twitter/sebdedeyne/1181838273049743360/1181856401167134720",
    "wm-target": "https://sebastiandedeyne.com/migrating-my-site-to-hugo/",
    "content": {
      "html": "sure, see no real reason why not\n<a class=\"u-mention\" href=\"https://sebastiandedeyne.com/\"></a>\n<a class=\"u-mention\" href=\"https://twitter.com/GoHugoIO\"></a>\n<a class=\"u-mention\" href=\"https://twitter.com/christophrumpel\"></a>\n<a class=\"u-mention\" href=\"https://twitter.com/sebdedeyne\"></a>",
      "text": "sure, see no real reason why not"
    },
    "in-reply-to": "https://sebastiandedeyne.com/migrating-my-site-to-hugo/",
    "wm-property": "in-reply-to",
    "wm-private": false
  },
  {
    "type": "entry",
    "author": {
      "type": "card",
      "name": "Frederick Vanbrabant",
      "photo": "https://webmention.io/avatar/pbs.twimg.com/79ec01dbe39d77912093887ec2c4d304d2885330d843f45e1bbf4a69c221164a.jpg",
      "url": "https://twitter.com/maybeFrederick"
    },
    "url": "https://twitter.com/maybeFrederick/status/1181851726258868224",
    "published": "2019-10-09T08:39:43+00:00",
    "wm-received": "2019-10-09T09:00:01Z",
    "wm-id": 707487,
    "wm-source": "https://brid-gy.appspot.com/comment/twitter/sebdedeyne/1181838273049743360/1181851726258868224",
    "wm-target": "https://sebastiandedeyne.com/migrating-my-site-to-hugo/",
    "content": {
      "html": "My site is also Hugo, Love everything about it!\n<a class=\"u-mention\" href=\"https://sebastiandedeyne.com/\"></a>\n<a class=\"u-mention\" href=\"https://twitter.com/GoHugoIO\"></a>\n<a class=\"u-mention\" href=\"https://twitter.com/christophrumpel\"></a>\n<a class=\"u-mention\" href=\"https://twitter.com/sebdedeyne\"></a>",
      "text": "My site is also Hugo, Love everything about it!"
    },
    "in-reply-to": "https://sebastiandedeyne.com/migrating-my-site-to-hugo/",
    "wm-property": "in-reply-to",
    "wm-private": false
  },
  {
    "type": "entry",
    "author": {
      "type": "card",
      "name": "Christoph Rumpel 🤠",
      "photo": "https://webmention.io/avatar/pbs.twimg.com/6a9353f47bff347ef06aa35069a69e19064f5499e29fc411ead1250cac6b9013.jpg",
      "url": "https://twitter.com/christophrumpel"
    },
    "url": "https://twitter.com/christophrumpel/status/1181853650613936128",
    "published": "2019-10-09T08:47:22+00:00",
    "wm-received": "2019-10-09T09:00:03Z",
    "wm-id": 707488,
    "wm-source": "https://brid-gy.appspot.com/comment/twitter/sebdedeyne/1181838273049743360/1181853650613936128",
    "wm-target": "https://sebastiandedeyne.com/migrating-my-site-to-hugo/",
    "content": {
      "html": "Cool. Would I be able to insert tweets or sort a list of talks depending if they are in the past or future?\n<a class=\"u-mention\" href=\"https://sebastiandedeyne.com/\"></a>\n<a class=\"u-mention\" href=\"https://twitter.com/GoHugoIO\"></a>\n<a class=\"u-mention\" href=\"https://twitter.com/maybeFrederick\"></a>\n<a class=\"u-mention\" href=\"https://twitter.com/sebdedeyne\"></a>",
      "text": "Cool. Would I be able to insert tweets or sort a list of talks depending if they are in the past or future?"
    },
    "in-reply-to": "https://sebastiandedeyne.com/migrating-my-site-to-hugo/",
    "wm-property": "in-reply-to",
    "wm-private": false
  },
  {
    "type": "entry",
    "author": {
      "type": "card",
      "name": "Spatie",
      "photo": "https://webmention.io/avatar/pbs.twimg.com/3efb487e7f3a0bc3690580277105f93eda590d65e4d9eb01135a184a9df60b18.jpg",
      "url": "https://twitter.com/spatie_be"
    },
    "url": "https://twitter.com/spatie_be/status/1181857401919680512",
    "published": "2019-10-09T09:02:17+00:00",
    "wm-received": "2019-10-09T09:35:08Z",
    "wm-id": 707510,
    "wm-source": "https://brid-gy.appspot.com/repost/twitter/sebdedeyne/1181838273049743360/1181857401919680512",
    "wm-target": "https://sebastiandedeyne.com/migrating-my-site-to-hugo/",
    "content": {
      "text": "I migrated my site to @GoHugoIO a few months ago, and I'm still very happy with the decision!\n\nsebastiandedeyne.com/migrating-my-s…"
    },
    "repost-of": "https://sebastiandedeyne.com/migrating-my-site-to-hugo/",
    "wm-property": "repost-of",
    "wm-private": false
  },
  {
    "type": "entry",
    "author": {
      "type": "card",
      "name": "Sebastian De Deyne",
      "photo": "https://webmention.io/avatar/pbs.twimg.com/3ce609991342657b8b7e99eb7a5c6e3656fbdb1c51575f1464d354b81aaeda86.jpg",
      "url": "https://twitter.com/sebdedeyne"
    },
    "url": "https://twitter.com/sebdedeyne/status/1181862889327661056",
    "published": "2019-10-09T09:24:05+00:00",
    "wm-received": "2019-10-09T09:35:10Z",
    "wm-id": 707511,
    "wm-source": "https://brid-gy.appspot.com/comment/twitter/sebdedeyne/1181838273049743360/1181862889327661056",
    "wm-target": "https://sebastiandedeyne.com/migrating-my-site-to-hugo/",
    "content": {
      "html": "Yep! You need some determination though, the Go templates take a while to get used to, especially for data transformations\n<a class=\"u-mention\" href=\"https://twitter.com/GoHugoIO\"></a>\n<a class=\"u-mention\" href=\"https://twitter.com/christophrumpel\"></a>\n<a class=\"u-mention\" href=\"https://twitter.com/maybeFrederick\"></a>",
      "text": "Yep! You need some determination though, the Go templates take a while to get used to, especially for data transformations"
    },
    "in-reply-to": "https://sebastiandedeyne.com/migrating-my-site-to-hugo/",
    "wm-property": "in-reply-to",
    "wm-private": false
  },
  {
    "type": "entry",
    "author": {
      "type": "card",
      "name": "Martijn Thomas",
      "photo": "https://webmention.io/avatar/pbs.twimg.com/8c7c88435f042c32d36b271f09a3f78a4760532fb86fcf5d8ef7f20cb6c17a9f.jpg",
      "url": "https://twitter.com/MartijnThomas"
    },
    "url": "https://twitter.com/sebdedeyne/status/1181838273049743360#favorited-by-19978140",
    "published": null,
    "wm-received": "2019-10-09T09:35:12Z",
    "wm-id": 707512,
    "wm-source": "https://brid-gy.appspot.com/like/twitter/sebdedeyne/1181838273049743360/19978140",
    "wm-target": "https://sebastiandedeyne.com/migrating-my-site-to-hugo/",
    "like-of": "https://sebastiandedeyne.com/migrating-my-site-to-hugo/",
    "wm-property": "like-of",
    "wm-private": false
  },
  {
    "type": "entry",
    "author": {
      "type": "card",
      "name": "Cyril de Wit",
      "photo": "https://webmention.io/avatar/pbs.twimg.com/024226e454853ac712e85cd3c646b7f3aea99b8adb6399176042dbc5db88903c.jpg",
      "url": "https://twitter.com/cyrildewit"
    },
    "url": "https://twitter.com/sebdedeyne/status/1181838273049743360#favorited-by-2172253302",
    "published": null,
    "wm-received": "2019-10-09T09:35:15Z",
    "wm-id": 707513,
    "wm-source": "https://brid-gy.appspot.com/like/twitter/sebdedeyne/1181838273049743360/2172253302",
    "wm-target": "https://sebastiandedeyne.com/migrating-my-site-to-hugo/",
    "like-of": "https://sebastiandedeyne.com/migrating-my-site-to-hugo/",
    "wm-property": "like-of",
    "wm-private": false
  },
  {
    "type": "entry",
    "author": {
      "type": "card",
      "name": "Ian Mostar",
      "photo": "https://webmention.io/avatar/pbs.twimg.com/18393e019737a72b2c366db40e9bad59bdd5edcf359807b0a7b62c5a06e9930e.png",
      "url": "https://twitter.com/iiianous"
    },
    "url": "https://twitter.com/sebdedeyne/status/1181838273049743360#favorited-by-3105517370",
    "published": null,
    "wm-received": "2019-10-09T10:40:32Z",
    "wm-id": 707540,
    "wm-source": "https://brid-gy.appspot.com/like/twitter/sebdedeyne/1181838273049743360/3105517370",
    "wm-target": "https://sebastiandedeyne.com/migrating-my-site-to-hugo/",
    "like-of": "https://sebastiandedeyne.com/migrating-my-site-to-hugo/",
    "wm-property": "like-of",
    "wm-private": false
  },
  {
    "type": "entry",
    "author": {
      "type": "card",
      "name": "mustaq ahmed",
      "photo": "https://webmention.io/avatar/pbs.twimg.com/a7946d73b154f00a6b334a910e3e1bdc5ab803a12bf62984aada5095e4b36306.jpg",
      "url": "https://twitter.com/hellomustaq"
    },
    "url": "https://twitter.com/sebdedeyne/status/1181838273049743360#favorited-by-2350460675",
    "published": null,
    "wm-received": "2019-10-11T01:33:32Z",
    "wm-id": 708626,
    "wm-source": "https://brid-gy.appspot.com/like/twitter/sebdedeyne/1181838273049743360/2350460675",
    "wm-target": "https://sebastiandedeyne.com/migrating-my-site-to-hugo/",
    "like-of": "https://sebastiandedeyne.com/migrating-my-site-to-hugo/",
    "wm-property": "like-of",
    "wm-private": false
  }
]